newonder_sentry_log/__init__.py
newonder_sentry_log/sentry.py
newonder_sentry_log-1.0.2.dist-info/METADATA
newonder_sentry_log-1.0.2.dist-info/WHEEL
newonder_sentry_log-1.0.2.dist-info/top_level.txt
newonder_sentry_log-1.0.2.dist-info/RECORD
