Metadata-Version: 2.1
Name: newonder-sentry-log
Version: 1.0.2
Summary: A logging package that integrates with Sentry for Newonder projects
Author: wangsw
Author-email: wangshiwei@xinhuadu.com.cn
Classifier: Development Status :: 4 - Beta
Classifier: Intended Audience :: Developers
Classifier: License :: OSI Approved :: MIT License
Classifier: Operating System :: OS Independent
Classifier: Programming Language :: Python :: 3
Classifier: Programming Language :: Python :: 3.7
Classifier: Programming Language :: Python :: 3.8
Classifier: Programming Language :: Python :: 3.9
Classifier: Programming Language :: Python :: 3.10
Requires-Python: >=3.7
Requires-Dist: sentry-sdk>=1.0.0
